MeetupAPI/__init__.py
MeetupAPI/log.py
MeetupAPI/meetup.py
MeetupAPI/meetup_functions/__init__.py
MeetupAPI/meetup_functions/access_token.py
MeetupAPI/meetup_functions/create.py
MeetupAPI/meetup_functions/delete.py
MeetupAPI/meetup_functions/events.py
MeetupAPI/meetup_functions/group.py
MeetupAPI/meetup_functions/int_timezoneToOffset.py
MeetupAPI/meetup_functions/list_offsetToTimezone.py
MeetupAPI/meetup_functions/meetup_fields.py
MeetupAPI/meetup_functions/message.py
MeetupAPI/meetup_functions/message_group_organizer.py
MeetupAPI/meetup_functions/str_location.py
MeetupAPI/meetup_functions/str_timezone.py
MeetupAPI/meetup_functions/text_series_timing.py
MeetupAPI/meetup_functions/upcoming_events.py
meetup_api/__init__.py
meetup_api/log.py
meetup_api/meetup.py
meetup_api/meetup_functions/__init__.py
meetup_api/meetup_functions/access_token.py
meetup_api/meetup_functions/create.py
meetup_api/meetup_functions/delete.py
meetup_api/meetup_functions/events.py
meetup_api/meetup_functions/int_timezoneToOffset.py
meetup_api/meetup_functions/list_offsetToTimezone.py
meetup_api/meetup_functions/meetup_fields.py
meetup_api/meetup_functions/str_location.py
meetup_api/meetup_functions/str_timezone.py
meetup_api/meetup_functions/text_series_timing.py
MeetupAPI-1.5.8.dist-info/LICENSE
MeetupAPI-1.5.8.dist-info/METADATA
MeetupAPI-1.5.8.dist-info/WHEEL
MeetupAPI-1.5.8.dist-info/top_level.txt
MeetupAPI-1.5.8.dist-info/RECORD
