Metadata-Version: 2.1
Name: MeetupAPI
Version: 1.5.8
Summary: Use the combined power of the official Meetup API and a web scraper to implement Meetup into your project.
Home-page: https://github.com/glowingkitty/Meetup-API
Author: Marco
License: UNKNOWN
Platform: UNKNOWN
Classifier: Programming Language :: Python :: 3
Classifier: License :: OSI Approved :: MIT License
Classifier: Operating System :: OS Independent
Requires-Python: >=3.6
Requires-Dist: requests
Requires-Dist: PyWebScraper
Requires-Dist: geopy
Requires-Dist: langdetect
